{
  "content": {
    "Início": {
      "title": "Início",
      "href": "/"
    },
    "Formação": {
      "title": "Formação",
      "href": "/formacao"
    },
    "Parceiras": {
      "title": "Parceiras",
      "href": "/parceiras"
    },
    "Pesquisa": {
      "title": "Pesquisa",
      "href": "/pesquisa"
    },
    "Contato": {
      "title": "Contato",
      "href": "/contato"
    },
    "Notícias": {
      "title": "Notícias",
      "href": "/noticias"
    },
    "Sobre": {
      "title": "Sobre",
      "href": "/sobre"
    }
  }
}